claydates/__init__.py
claydates/datasets/currencyPairs.txt
claydates/datasets/exampleSet.csv
claydates/datasets/key.txt
claydates/datasets/missingDataLog.csv
claydates/examples/__init__.py
claydates/examples/examplesMultiTickerPlotter.py
claydates/examples/examplesMultiTickerProcessor.py
claydates/examples/examplesSingleTickerPlotter.py
claydates/examples/examplesSingleTickerProcessor.py
claydates/plotters/__init__.py
claydates/plotters/multiTickerPlotter.py
claydates/plotters/singleTickerPlotter.py
claydates/processors/__init__.py
claydates/processors/multiTickerProcessor.py
claydates/processors/singleTickerProcessor.py
claydates-1.0.6.dist-info/LICENSE
claydates-1.0.6.dist-info/METADATA
claydates-1.0.6.dist-info/WHEEL
claydates-1.0.6.dist-info/top_level.txt
claydates-1.0.6.dist-info/RECORD
