Metadata-Version: 2.1
Name: claydates
Version: 1.0.6
Summary: Package used for cleaning, restructuring, logging, and plotting of financial data retrieved from the Twelve Data API.
Home-page: https://github.com/ClaytonDuffin/claydates
Author: Clayton Duffin
Author-email: clayduffin@gmail.com
Keywords: twelvedata API,restructuring,cleaning,plotting,financial data
Classifier: Development Status :: 5 - Production/Stable
Classifier: Intended Audience :: Developers
Classifier: License :: OSI Approved :: MIT License
Classifier: Programming Language :: Python :: 3.9
Requires-Dist: matplotlib
Requires-Dist: numpy
Requires-Dist: pandas
Requires-Dist: pandas-market-calendars
Requires-Dist: python-dateutil
Requires-Dist: requests
Requires-Dist: twelvedata
